whendo/__init__.py
whendo/_version.py
whendo/api/__init__.py
whendo/api/main.py
whendo/api/main_temp.py
whendo/api/shared.py
whendo/api/router/__init__.py
whendo/api/router/actions.py
whendo/api/router/dispatcher.py
whendo/api/router/execution.py
whendo/api/router/jobs.py
whendo/api/router/programs.py
whendo/api/router/schedulers.py
whendo/api/router/servers.py
whendo/core/__init__.py
whendo/core/action.py
whendo/core/dispatcher.py
whendo/core/exception.py
whendo/core/executor.py
whendo/core/hooks.py
whendo/core/mockpsutil.py
whendo/core/program.py
whendo/core/resolver.py
whendo/core/resolver_imports.py
whendo/core/scheduler.py
whendo/core/scheduling.py
whendo/core/server.py
whendo/core/timed.py
whendo/core/util.py
whendo/core/actions/__init__.py
whendo/core/actions/dispatch_action.py
whendo/core/actions/file_action.py
whendo/core/actions/http_action.py
whendo/core/actions/list_action.py
whendo/core/actions/sys_action.py
whendo/core/programs/__init__.py
whendo/core/programs/simple_program.py
whendo/core/schedulers/__init__.py
whendo/core/schedulers/timed_scheduler.py
whendo/log/__init__.py
whendo/log/init.py
whendo/sdk/__init__.py
whendo/sdk/client.py
whendo-0.0.3a18.dist-info/LICENSE
whendo-0.0.3a18.dist-info/METADATA
whendo-0.0.3a18.dist-info/WHEEL
whendo-0.0.3a18.dist-info/top_level.txt
whendo-0.0.3a18.dist-info/RECORD
